cli_telemetry/__init__.py
cli_telemetry/__main__.py
cli_telemetry/cli.py
cli_telemetry/telemetry.py
cli_telemetry/exporters/__init__.py
cli_telemetry/exporters/view_flame.py
cli_telemetry/instrumentation/__init__.py
cli_telemetry/instrumentation/instrument_click.py
cli_telemetry/instrumentation/instrument_httpx.py
cli_telemetry/instrumentation/instrument_subprocess.py
cli_telemetry/plugins/__init__.py
cli_telemetry/plugins/speedscope_plugin/__init__.py
cli_telemetry/plugins/speedscope_plugin/plugin.py
cli_telemetry/plugins/upload_plugin/__init__.py
cli_telemetry/plugins/upload_plugin/plugin.py
cli_telemetry/plugins/webapp_plugin/__init__.py
cli_telemetry/plugins/webapp_plugin/plugin.py
cli_telemetry/plugins/webapp_plugin/webapp_static/index.html
cli_telemetry/plugins/webapp_plugin/webapp_static/main.js
cli_telemetry/plugins/webapp_plugin/webapp_static/style.css
cli_telemetry-0.0.2.dist-info/licenses/LICENSE
tests/test_telemetry.py
cli_telemetry-0.0.2.dist-info/METADATA
cli_telemetry-0.0.2.dist-info/WHEEL
cli_telemetry-0.0.2.dist-info/entry_points.txt
cli_telemetry-0.0.2.dist-info/top_level.txt
cli_telemetry-0.0.2.dist-info/RECORD
