Metadata-Version: 2.4
Name: cli-telemetry
Version: 0.0.2
Summary: OpenTelemetry-based instrumentation for CLI tools
Author-email: Amjith Ramanujam <amjith.r@gmail.com>
License: BSD
Project-URL: Homepage, https://github.com/amjith/cli-telemetry
Project-URL: Repository, https://github.com/amjith/cli-telemetry
Requires-Python: >=3.10
License-File: LICENSE
Requires-Dist: rich
Requires-Dist: click
Requires-Dist: tomli>=2.0
Provides-Extra: dev
Requires-Dist: pytest>=7.0; extra == "dev"
Requires-Dist: ruff>=0.11.8; extra == "dev"
Requires-Dist: coverage; extra == "dev"
Requires-Dist: tox>=4.8.0; extra == "dev"
Requires-Dist: flask>=2.0; extra == "dev"
Requires-Dist: flask-cors>=3.0; extra == "dev"
Provides-Extra: web
Requires-Dist: flask>=2.0; extra == "web"
Requires-Dist: flask-cors>=3.0; extra == "web"
Dynamic: license-file
